README.rst
setup.cfg
setup.py
ddtrace/__init__.py
ddtrace/api.py
ddtrace/compat.py
ddtrace/compat_async.py
ddtrace/constants.py
ddtrace/context.py
ddtrace/encoding.py
ddtrace/filters.py
ddtrace/helpers.py
ddtrace/monkey.py
ddtrace/pin.py
ddtrace/provider.py
ddtrace/sampler.py
ddtrace/settings.py
ddtrace/span.py
ddtrace/tracer.py
ddtrace/util.py
ddtrace/writer.py
ddtrace/bootstrap/__init__.py
ddtrace/bootstrap/sitecustomize.py
ddtrace/commands/__init__.py
ddtrace/commands/ddtrace_run.py
ddtrace/contrib/__init__.py
ddtrace/contrib/util.py
ddtrace/contrib/MySQLdb/__init__.py
ddtrace/contrib/MySQLdb/patch.py
ddtrace/contrib/aiobotocore/__init__.py
ddtrace/contrib/aiobotocore/patch.py
ddtrace/contrib/aiohttp/__init__.py
ddtrace/contrib/aiohttp/middlewares.py
ddtrace/contrib/aiohttp/patch.py
ddtrace/contrib/aiohttp/template.py
ddtrace/contrib/aiopg/__init__.py
ddtrace/contrib/aiopg/connection.py
ddtrace/contrib/aiopg/patch.py
ddtrace/contrib/asyncio/__init__.py
ddtrace/contrib/asyncio/helpers.py
ddtrace/contrib/asyncio/patch.py
ddtrace/contrib/asyncio/provider.py
ddtrace/contrib/boto/__init__.py
ddtrace/contrib/boto/patch.py
ddtrace/contrib/botocore/__init__.py
ddtrace/contrib/botocore/patch.py
ddtrace/contrib/bottle/__init__.py
ddtrace/contrib/bottle/patch.py
ddtrace/contrib/bottle/trace.py
ddtrace/contrib/cassandra/__init__.py
ddtrace/contrib/cassandra/patch.py
ddtrace/contrib/cassandra/session.py
ddtrace/contrib/celery/__init__.py
ddtrace/contrib/celery/app.py
ddtrace/contrib/celery/patch.py
ddtrace/contrib/celery/registry.py
ddtrace/contrib/celery/task.py
ddtrace/contrib/celery/util.py
ddtrace/contrib/cherrypy/__init__.py
ddtrace/contrib/cherrypy/middleware.py
ddtrace/contrib/dbapi/__init__.py
ddtrace/contrib/django/__init__.py
ddtrace/contrib/django/apps.py
ddtrace/contrib/django/cache.py
ddtrace/contrib/django/compat.py
ddtrace/contrib/django/conf.py
ddtrace/contrib/django/db.py
ddtrace/contrib/django/middleware.py
ddtrace/contrib/django/patch.py
rs_ddtrace.egg-info/PKG-INFO
rs_ddtrace.egg-info/SOURCES.txt
rs_ddtrace.egg-info/dependency_links.txt
rs_ddtrace.egg-info/entry_points.txt
rs_ddtrace.egg-info/requires.txt
rs_ddtrace.egg-info/top_level.txt