Metadata-Version: 1.1
Name: rs-ddtrace
Version: 0.12.1
Summary: Datadog tracing code
Home-page: https://github.com/DataDog/dd-trace-py
Author: Datadog, Inc.
Author-email: dev@datadoghq.com
License: BSD
Platform: UNKNOWN
Classifier: Programming Language :: Python
Classifier: Programming Language :: Python :: 2.7
Classifier: Programming Language :: Python :: 3.4
Classifier: Programming Language :: Python :: 3.5
Classifier: Programming Language :: Python :: 3.6
